game_to_pypi/__init__.py
game_to_pypi/game.py
game_to_pypi/gui.py
game_to_pypi/market.py
game_to_pypi/user.py
gtpp-0.1.0.dist-info/METADATA
gtpp-0.1.0.dist-info/WHEEL
gtpp-0.1.0.dist-info/entry_points.txt
gtpp-0.1.0.dist-info/top_level.txt
gtpp-0.1.0.dist-info/RECORD
