Metadata-Version: 2.4
Name: gtpp
Version: 0.1.0
Summary: Game To PyPI - Virtual pet game with PYPI, Coding for play, not for make game
Home-page: https://github.com/rabertsa/gtpp
Author: Ahmet ELCI
Classifier: Programming Language :: Python :: 3
Classifier: License :: OSI Approved :: MIT License
Classifier: Operating System :: OS Independent
Requires-Python: >=3.8
Requires-Dist: kivy>=2.2.0
Dynamic: author
Dynamic: classifier
Dynamic: home-page
Dynamic: requires-dist
Dynamic: requires-python
Dynamic: summary
